linkml_browser/__init__.py
linkml_browser/core.py
linkml_browser/index.html
linkml_browser/main.py
linkml_browser-0.1.0.dist-info/METADATA
linkml_browser-0.1.0.dist-info/WHEEL
linkml_browser-0.1.0.dist-info/entry_points.txt
linkml_browser-0.1.0.dist-info/RECORD
