Metadata-Version: 2.4
Name: linkml-browser
Version: 0.1.0
Summary: Add your description here
Author-email: Chris Mungall <cjm@berkeleybop.org>
Requires-Python: >=3.12
Requires-Dist: linkml-store>=0.2.11
Requires-Dist: linkml>=1.9.3
Requires-Dist: typer>=0.9.0
